{
  "project_info": {
    "project_number": "3768713961",
    "project_id": "kiko-chrono",
    "storage_bucket": "kiko-chrono.firebasestorage.app"
  },
  "client": [
    {
      "client_info": {
        "mobilesdk_app_id": "1:3768713961:android:710692d814161e48dba678",
        "android_client_info": {
          "package_name": "com.pierretulle.juno2"
        }
      },
      "oauth_client": [
        {
          "client_id": "3768713961-i1017vkh4srhomkom6bmbo8qjleqsi53.apps.googleusercontent.com",
          "client_type": 3
        }
      ],
      "api_key": [
        {
          "current_key": "AIzaSyDO9Z8eT-_G9OkGCKGWa4SXaqwPked1AaA"
        },
        {
          "current_key": "AIzaSyCJ0ZU0xEF-Me0CNpvZZ8BAm1oJquJlBIo"
        }
      ],
      "services": {
        "appinvite_service": {
          "other_platform_oauth_client": [
            {
              "client_id": "3768713961-i1017vkh4srhomkom6bmbo8qjleqsi53.apps.googleusercontent.com",
              "client_type": 3
            }
          ]
        }
      }
    },
    {
      "client_info": {
        "mobilesdk_app_id": "1:3768713961:android:426ace7690028338dba678",
        "android_client_info": {
          "package_name": "com.pierretulle.juno2.dev"
        }
      },
      "oauth_client": [
        {
          "client_id": "3768713961-i1017vkh4srhomkom6bmbo8qjleqsi53.apps.googleusercontent.com",
          "client_type": 3
        }
      ],
      "api_key": [
        {
          "current_key": "AIzaSyDO9Z8eT-_G9OkGCKGWa4SXaqwPked1AaA"
        },
        {
          "current_key": "AIzaSyCJ0ZU0xEF-Me0CNpvZZ8BAm1oJquJlBIo"
        }
      ],
      "services": {
        "appinvite_service": {
          "other_platform_oauth_client": [
            {
              "client_id": "3768713961-i1017vkh4srhomkom6bmbo8qjleqsi53.apps.googleusercontent.com",
              "client_type": 3
            }
          ]
        }
      }
    },
    {
      "client_info": {
        "mobilesdk_app_id": "1:3768713961:android:553a62091d035feddba678",
        "android_client_info": {
          "package_name": "com.pierretulle.kiko"
        }
      },
      "oauth_client": [
        {
          "client_id": "3768713961-i1017vkh4srhomkom6bmbo8qjleqsi53.apps.googleusercontent.com",
          "client_type": 3
        }
      ],
      "api_key": [
        {
          "current_key": "AIzaSyDO9Z8eT-_G9OkGCKGWa4SXaqwPked1AaA"
        },
        {
          "current_key": "AIzaSyCJ0ZU0xEF-Me0CNpvZZ8BAm1oJquJlBIo"
        }
      ],
      "services": {
        "appinvite_service": {
          "other_platform_oauth_client": [
            {
              "client_id": "3768713961-i1017vkh4srhomkom6bmbo8qjleqsi53.apps.googleusercontent.com",
              "client_type": 3
            }
          ]
        }
      }
    }
  ],
  "configuration_version": "1"
}